libsbgnpy/__init__.py
libsbgnpy/console.py
libsbgnpy/image.py
libsbgnpy/io.py
libsbgnpy/render.py
libsbgnpy/sbgn.py
libsbgnpy/validator.py
libsbgnpy/examples/__init__.py
libsbgnpy/examples/clone_marker_example.py
libsbgnpy/examples/ethanol_example.png
libsbgnpy/examples/ethanol_example.py
libsbgnpy/examples/ethanol_example_arcs.png
libsbgnpy/examples/ethanol_example_arcs.sbgn
libsbgnpy/examples/ethanol_example_glyphs.png
libsbgnpy/examples/ethanol_example_glyphs.sbgn
libsbgnpy/examples/ethanol_example_glyphs_render.png
libsbgnpy/examples/ethanol_example_render.sbgn
libsbgnpy/examples/extension_example.py
libsbgnpy/examples/info_example.py
libsbgnpy/examples/notes_example.py
libsbgnpy/examples/read_example.py
libsbgnpy/examples/render_example.py
libsbgnpy/examples/special_character_example.py
libsbgnpy/examples/write_example.py
libsbgnpy/examples/sbgn/adh.sbgn
libsbgnpy/examples/sbgn/adh_0.3.sbgn
libsbgnpy/examples/sbgn/extension.sbgn
libsbgnpy/examples/sbgn/glycolysis.sbgn
libsbgnpy/examples/sbgn/neuronal_muscle_signalling_color.sbgn
libsbgnpy/examples/sbgn/notes.sbgn
libsbgnpy/examples/sbgn/notes_new.sbgn
libsbgnpy/examples/sbgn/render.sbgn
libsbgnpy/examples/sbgn/test-output-01-old.sbgn
libsbgnpy/examples/sbgn/test-output-01.sbgn
libsbgnpy/examples/sbgn/test-output-02-old.sbgn
libsbgnpy/examples/sbgn/test-output-02.sbgn
libsbgnpy/examples/sbgn/test-output-03-old.sbgn
libsbgnpy/examples/sbgn/test-output-03.sbgn
libsbgnpy/sbo/sbgn_sbo_mapping.txt
libsbgnpy/sbo/sbo2sbgn.py
libsbgnpy/sbo/sbo_sbgn_map.txt
libsbgnpy/schema/README.md
libsbgnpy/schema/SBGN.xsd
libsbgnpy/schema/render.xsd
libsbgnpy-0.4.1.dist-info/METADATA
libsbgnpy-0.4.1.dist-info/WHEEL
libsbgnpy-0.4.1.dist-info/licenses/LICENSE
libsbgnpy-0.4.1.dist-info/RECORD
