Metadata-Version: 2.4
Name: libsbgnpy
Version: 0.4.1
Summary: libsbgnpy are python utilities for working with SBGN.
Author-email: Matthias König <konigmatt@googlemail.com>
Maintainer-email: Matthias König <konigmatt@googlemail.com>
License-File: LICENSE
Keywords: COMBINE,SBGN,modeling,standardization
Classifier: Development Status :: 4 - Beta
Classifier: Intended Audience :: Science/Research
Classifier: License :: OSI Approved :: MIT License
Classifier: Operating System :: OS Independent
Classifier: Programming Language :: Python :: 3.10
Classifier: Programming Language :: Python :: 3.11
Classifier: Programming Language :: Python :: 3.12
Classifier: Programming Language :: Python :: 3.13
Classifier: Programming Language :: Python :: Implementation :: CPython
Classifier: Topic :: Scientific/Engineering
Classifier: Topic :: Scientific/Engineering :: Bio-Informatics
Requires-Python: >=3.10
Requires-Dist: lxml>=5.3
Requires-Dist: requests
Requires-Dist: rich
Requires-Dist: xsdata
Provides-Extra: dev
Requires-Dist: bump-my-version>=0.29.0; extra == 'dev'
Requires-Dist: mypy>=1.9.0; extra == 'dev'
Requires-Dist: pre-commit>=4.0.1; extra == 'dev'
Requires-Dist: pytest>=8.1.1; extra == 'dev'
Requires-Dist: ruff>=0.8.6; extra == 'dev'
Provides-Extra: docs
Requires-Dist: ipython; extra == 'docs'
Requires-Dist: mkdocs; extra == 'docs'
Requires-Dist: mkdocs-jupyter; extra == 'docs'
Requires-Dist: mkdocs-material; extra == 'docs'
Requires-Dist: mkdocstrings-python; extra == 'docs'
Provides-Extra: test
Requires-Dist: pytest-cov>=5.0.0; extra == 'test'
Requires-Dist: pytest>=8.1.1; extra == 'test'
Requires-Dist: tox>=4.14.2; extra == 'test'
